flask_buzz/__init__.py
flask_buzz/base.py
flask_buzz/py.typed
flask_buzz-4.0.0.dist-info/METADATA
flask_buzz-4.0.0.dist-info/WHEEL
flask_buzz-4.0.0.dist-info/licenses/LICENSE.md
flask_buzz-4.0.0.dist-info/RECORD
