Metadata-Version: 2.4
Name: flask-buzz
Version: 4.0.0
Summary: Extra bindings on py-buzz specifically for flask apps
Project-URL: homepage, https://github.com/dusktreader/flask-buzz
Project-URL: source, https://github.com/dusktreader/flask-buzz
Project-URL: changelog, https://github.com/dusktreader/flask-buzz/blob/main/CHANGELOG.md
Author-email: Tucker Beck <tucker.beck@gmail.com>
License-File: LICENSE.md
Requires-Python: >=3.10
Requires-Dist: flask<4.0,>=2.0
Requires-Dist: py-buzz~=7.0
